{
  "date": "2025-05-08",
  "ticker": "0015B0",
  "fund_id": "2ETFQ1",
  "name": "KoAct 미국나스닥성장기업액티브",
  "count": 37,
  "holdings": [
    {
      "isin": "US69608A1088",
      "name": "Palantir Technologies Inc -A",
      "code": "PLTR US Equity",
      "ticker": "PLTR",
      "weight": 12.983,
      "shares": 350,
      "amount": 53249979.0,
      "price": null,
      "is_cash": false,
      "key": "US69608A1088",
      "price_usd": 119.15
    },
    {
      "isin": "US88160R1014",
      "name": "TESLA MOTORS",
      "code": "TSLA US Equity",
      "ticker": "TSLA",
      "weight": 11.466,
      "shares": 122,
      "amount": 47028034.0,
      "price": null,
      "is_cash": false,
      "key": "US88160R1014",
      "price_usd": 284.82
    },
    {
      "isin": "US02079K3059",
      "name": "ALPHABET INC-CL A",
      "code": "GOOGL US Equity",
      "ticker": "GOOGL",
      "weight": 7.7096,
      "shares": 139,
      "amount": 31621055.0,
      "price": null,
      "is_cash": false,
      "key": "US02079K3059",
      "price_usd": 154.28
    },
    {
      "isin": "US67066G1040",
      "name": "NVIDIA Corp",
      "code": "NVDA US Equity",
      "ticker": "NVDA",
      "weight": 5.7075,
      "shares": 147,
      "amount": 23409341.0,
      "price": null,
      "is_cash": false,
      "key": "US67066G1040",
      "price_usd": 117.37
    },
    {
      "isin": "US5949724083",
      "name": "MicroStrategy Inc",
      "code": "MSTR US Equity",
      "ticker": "MSTR",
      "weight": 4.7289,
      "shares": 36,
      "amount": 19395695.0,
      "price": null,
      "is_cash": false,
      "key": "US5949724083",
      "price_usd": 414.38
    },
    {
      "isin": "US4464131063",
      "name": "HUNTINGTON INGALLS INDUSTRIE",
      "code": "HII US Equity",
      "ticker": "HII",
      "weight": 4.3605,
      "shares": 55,
      "amount": 17884889.0,
      "price": null,
      "is_cash": false,
      "key": "US4464131063",
      "price_usd": 232.95
    },
    {
      "isin": "US11135F1012",
      "name": "BROADCOM LTD",
      "code": "AVGO US Equity",
      "ticker": "AVGO",
      "weight": 3.9788,
      "shares": 58,
      "amount": 16319204.0,
      "price": null,
      "is_cash": false,
      "key": "US11135F1012",
      "price_usd": 207.77
    },
    {
      "isin": "US64110L1061",
      "name": "NETFLIX",
      "code": "NFLX US Equity",
      "ticker": "NFLX",
      "weight": 3.5831,
      "shares": 9,
      "amount": 14696133.0,
      "price": null,
      "is_cash": false,
      "key": "US64110L1061",
      "price_usd": 114.44
    },
    {
      "isin": "US7710491033",
      "name": "Roblox Coperation",
      "code": "RBLX US Equity",
      "ticker": "RBLX",
      "weight": 3.1667,
      "shares": 131,
      "amount": 12988378.0,
      "price": null,
      "is_cash": false,
      "key": "US7710491033",
      "price_usd": 70.05
    },
    {
      "isin": "US36828A1016",
      "name": "GE Vernova LLC",
      "code": "GEV US Equity",
      "ticker": "GEV",
      "weight": 2.8692,
      "shares": 21,
      "amount": 11768091.0,
      "price": null,
      "is_cash": false,
      "key": "US36828A1016",
      "price_usd": 394.0
    },
    {
      "isin": "US01609W1027",
      "name": "ALIBABA GROUP HOLDING-SP ADR",
      "code": "BABA US Equity",
      "ticker": "BABA",
      "weight": 2.7,
      "shares": 62,
      "amount": 11073981.0,
      "price": null,
      "is_cash": false,
      "key": "US01609W1027",
      "price_usd": 125.79
    },
    {
      "isin": "US30303M1027",
      "name": "Meta Platforms Inc-CL A",
      "code": "META US Equity",
      "ticker": "META",
      "weight": 2.2361,
      "shares": 11,
      "amount": 9171233.0,
      "price": null,
      "is_cash": false,
      "key": "US30303M1027",
      "price_usd": 598.01
    },
    {
      "isin": "US26603R1068",
      "name": "Duolingo Inc",
      "code": "DUOL US Equity",
      "ticker": "DUOL",
      "weight": 2.0984,
      "shares": 13,
      "amount": 8606650.0,
      "price": null,
      "is_cash": false,
      "key": "US26603R1068",
      "price_usd": 503.57
    },
    {
      "isin": "US18915M1071",
      "name": "Cloudflare Inc",
      "code": "NET US Equity",
      "ticker": "NET",
      "weight": 2.0958,
      "shares": 50,
      "amount": 8595940.0,
      "price": null,
      "is_cash": false,
      "key": "US18915M1071",
      "price_usd": 124.31
    },
    {
      "isin": "US19260Q1076",
      "name": "COINBASE GLOBAL INC -CLASS A",
      "code": "COIN US Equity",
      "ticker": "COIN",
      "weight": 1.9945,
      "shares": 30,
      "amount": 8180495.0,
      "price": null,
      "is_cash": false,
      "key": "US19260Q1076",
      "price_usd": 206.5
    },
    {
      "isin": "US6974351057",
      "name": "PALO ALTO NETWORKS INC",
      "code": "PANW US Equity",
      "ticker": "PANW",
      "weight": 1.9873,
      "shares": 31,
      "amount": 8151068.0,
      "price": null,
      "is_cash": false,
      "key": "US6974351057",
      "price_usd": 188.53
    },
    {
      "isin": "US98980G1022",
      "name": "ZSCALER INC",
      "code": "ZS US Equity",
      "ticker": "ZS",
      "weight": 1.9331,
      "shares": 24,
      "amount": 7928509.0,
      "price": null,
      "is_cash": false,
      "key": "US98980G1022",
      "price_usd": 233.15
    },
    {
      "isin": "US75734B1008",
      "name": "Reddit Inc",
      "code": "RDDT US Equity",
      "ticker": "RDDT",
      "weight": 1.9139,
      "shares": 51,
      "amount": 7849755.0,
      "price": null,
      "is_cash": false,
      "key": "US75734B1008",
      "price_usd": 107.83
    },
    {
      "isin": "US92840M1027",
      "name": "VISTRA ENERGY CORP",
      "code": "VST US Equity",
      "ticker": "VST",
      "weight": 1.8587,
      "shares": 38,
      "amount": 7623528.0,
      "price": null,
      "is_cash": false,
      "key": "US92840M1027",
      "price_usd": 140.91
    },
    {
      "isin": "US25809K1051",
      "name": "DOORDASH INC - A",
      "code": "DASH US Equity",
      "ticker": "DASH",
      "weight": 1.8357,
      "shares": 28,
      "amount": 7529371.0,
      "price": null,
      "is_cash": false,
      "key": "US25809K1051",
      "price_usd": 182.96
    },
    {
      "isin": "US90138F1021",
      "name": "TWILIO",
      "code": "TWLO US Equity",
      "ticker": "TWLO",
      "weight": 1.7928,
      "shares": 52,
      "amount": 7353316.0,
      "price": null,
      "is_cash": false,
      "key": "US90138F1021",
      "price_usd": 105.23
    },
    {
      "isin": "US5949181045",
      "name": "MICROSOFT",
      "code": "MSFT US Equity",
      "ticker": "MSFT",
      "weight": 1.7118,
      "shares": 12,
      "amount": 7020843.0,
      "price": null,
      "is_cash": false,
      "key": "US5949181045",
      "price_usd": 438.17
    },
    {
      "isin": "US88023B1035",
      "name": "Tempus AI Inc",
      "code": "TEM US Equity",
      "ticker": "TEM",
      "weight": 1.59,
      "shares": 89,
      "amount": 6521309.0,
      "price": null,
      "is_cash": false,
      "key": "US88023B1035",
      "price_usd": 65.22
    },
    {
      "isin": "US19247G1076",
      "name": "COHERENT CORP",
      "code": "COHR US Equity",
      "ticker": "COHR",
      "weight": 1.5241,
      "shares": 64,
      "amount": 6251080.0,
      "price": null,
      "is_cash": false,
      "key": "US19247G1076",
      "price_usd": 70.59
    },
    {
      "isin": "US26701L1008",
      "name": "Dutch Bros Inc",
      "code": "BROS US Equity",
      "ticker": "BROS",
      "weight": 1.3079,
      "shares": 64,
      "amount": 5364193.0,
      "price": null,
      "is_cash": false,
      "key": "US26701L1008",
      "price_usd": 64.45
    },
    {
      "isin": "US5324571083",
      "name": "ELI LILLY & CO",
      "code": "LLY US Equity",
      "ticker": "LLY",
      "weight": 1.1572,
      "shares": 4,
      "amount": 4746245.0,
      "price": null,
      "is_cash": false,
      "key": "US5324571083",
      "price_usd": 751.45
    },
    {
      "isin": "US8740541094",
      "name": "TAKE-TWO INTERACTIVE SOFTWRE",
      "code": "TTWO US Equity",
      "ticker": "TTWO",
      "weight": 1.1332,
      "shares": 14,
      "amount": 4647770.0,
      "price": null,
      "is_cash": false,
      "key": "US8740541094",
      "price_usd": 225.45
    },
    {
      "isin": "LU1778762911",
      "name": "Spotify Technology SA",
      "code": "SPOT US Equity",
      "ticker": "SPOT",
      "weight": 1.0419,
      "shares": 5,
      "amount": 4273218.0,
      "price": null,
      "is_cash": false,
      "key": "LU1778762911",
      "price_usd": 655.26
    },
    {
      "isin": "US7731221062",
      "name": "Rocket Lab USA Inc",
      "code": "RKLB US Equity",
      "ticker": "RKLB",
      "weight": 1.0152,
      "shares": 133,
      "amount": 4163721.0,
      "price": null,
      "is_cash": false,
      "key": "US7731221062",
      "price_usd": 23.1
    },
    {
      "isin": "US7181721090",
      "name": "PHILIP MORRIS INTERNATIONAL",
      "code": "PM US Equity",
      "ticker": "PM",
      "weight": 0.9921,
      "shares": 17,
      "amount": 4069043.0,
      "price": null,
      "is_cash": false,
      "key": "US7181721090",
      "price_usd": 172.0
    },
    {
      "isin": "US76655K1034",
      "name": "Rigetti Computing Inc",
      "code": "RGTI US Equity",
      "ticker": "RGTI",
      "weight": 0.9906,
      "shares": 297,
      "amount": 4062790.0,
      "price": null,
      "is_cash": false,
      "key": "US76655K1034",
      "price_usd": 10.31
    },
    {
      "isin": "US89677Q1076",
      "name": "TRIP.COM GROUP",
      "code": "TCOM US Equity",
      "ticker": "TCOM",
      "weight": 0.8987,
      "shares": 43,
      "amount": 3686170.0,
      "price": null,
      "is_cash": false,
      "key": "US89677Q1076",
      "price_usd": 61.97
    },
    {
      "isin": "US8760301072",
      "name": "TAPESTRY INC",
      "code": "TPR US Equity",
      "ticker": "TPR",
      "weight": 0.8513,
      "shares": 34,
      "amount": 3491745.0,
      "price": null,
      "is_cash": false,
      "key": "US8760301072",
      "price_usd": 77.54
    },
    {
      "isin": "US7707001027",
      "name": "Robinhood Markets Inc",
      "code": "HOOD US Equity",
      "ticker": "HOOD",
      "weight": 0.8172,
      "shares": 49,
      "amount": 3351698.0,
      "price": null,
      "is_cash": false,
      "key": "US7707001027",
      "price_usd": 54.07
    },
    {
      "isin": "CH1134540470",
      "name": "On Holding AG",
      "code": "ONON US Equity",
      "ticker": "ONON",
      "weight": 0.7257,
      "shares": 44,
      "amount": 2976333.0,
      "price": null,
      "is_cash": false,
      "key": "CH1134540470",
      "price_usd": 49.72
    },
    {
      "isin": "KYG8068L1086",
      "name": "SharkNinja Inc",
      "code": "SN US Equity",
      "ticker": "SN",
      "weight": 0.7039,
      "shares": 26,
      "amount": 2887237.0,
      "price": null,
      "is_cash": false,
      "key": "KYG8068L1086",
      "price_usd": 91.63
    },
    {
      "isin": "US92532F1003",
      "name": "Vertex Pharmaceuticals Inc",
      "code": "VRTX US Equity",
      "ticker": "VRTX",
      "weight": 0.5399,
      "shares": 4,
      "amount": 2214579.0,
      "price": null,
      "is_cash": false,
      "key": "US92532F1003",
      "price_usd": 429.6
    },
    {
      "isin": "CASH00000001",
      "name": "설정현금액",
      "code": "CASH00000001",
      "ticker": "",
      "weight": 0.0,
      "shares": 436796658,
      "amount": 436796658.0,
      "price": null,
      "is_cash": true,
      "key": "CASH00000001"
    },
    {
      "isin": "KRD010010001",
      "name": "원화현금",
      "code": "KRD010010001",
      "ticker": "",
      "weight": 0.0,
      "shares": 26644039,
      "amount": 26644039.0,
      "price": null,
      "is_cash": true,
      "key": "KRD010010001"
    }
  ]
}