{
  "date": "2025-05-07",
  "ticker": "0015B0",
  "fund_id": "2ETFQ1",
  "name": "KoAct 미국나스닥성장기업액티브",
  "count": 35,
  "holdings": [
    {
      "isin": "US69608A1088",
      "name": "Palantir Technologies Inc -A",
      "code": "PLTR US Equity",
      "ticker": "PLTR",
      "weight": 14.0342,
      "shares": 362,
      "amount": 59176786.0,
      "price": null,
      "is_cash": false,
      "key": "US69608A1088",
      "price_usd": 110.48
    },
    {
      "isin": "US88160R1014",
      "name": "TESLA MOTORS",
      "code": "TSLA US Equity",
      "ticker": "TSLA",
      "weight": 11.8303,
      "shares": 127,
      "amount": 49883935.0,
      "price": null,
      "is_cash": false,
      "key": "US88160R1014",
      "price_usd": 276.22
    },
    {
      "isin": "US02079K3059",
      "name": "ALPHABET INC-CL A",
      "code": "GOOGL US Equity",
      "ticker": "GOOGL",
      "weight": 7.7153,
      "shares": 144,
      "amount": 32532380.0,
      "price": null,
      "is_cash": false,
      "key": "US02079K3059",
      "price_usd": 151.38
    },
    {
      "isin": "US5949724083",
      "name": "MicroStrategy Inc",
      "code": "MSTR US Equity",
      "ticker": "MSTR",
      "weight": 4.7399,
      "shares": 37,
      "amount": 19986502.0,
      "price": null,
      "is_cash": false,
      "key": "US5949724083",
      "price_usd": 392.48
    },
    {
      "isin": "US67066G1040",
      "name": "NVIDIA Corp",
      "code": "NVDA US Equity",
      "ticker": "NVDA",
      "weight": 4.6403,
      "shares": 125,
      "amount": 19566480.0,
      "price": null,
      "is_cash": false,
      "key": "US67066G1040",
      "price_usd": 117.06
    },
    {
      "isin": "US4464131063",
      "name": "HUNTINGTON INGALLS INDUSTRIE",
      "code": "HII US Equity",
      "ticker": "HII",
      "weight": 4.313,
      "shares": 57,
      "amount": 18186461.0,
      "price": null,
      "is_cash": false,
      "key": "US4464131063",
      "price_usd": 230.21
    },
    {
      "isin": "US64110L1061",
      "name": "NETFLIX",
      "code": "NFLX US Equity",
      "ticker": "NFLX",
      "weight": 3.6152,
      "shares": 10,
      "amount": 15243721.0,
      "price": null,
      "is_cash": false,
      "key": "US64110L1061",
      "price_usd": 115.54
    },
    {
      "isin": "US11135F1012",
      "name": "BROADCOM LTD",
      "code": "AVGO US Equity",
      "ticker": "AVGO",
      "weight": 3.4481,
      "shares": 52,
      "amount": 14539250.0,
      "price": null,
      "is_cash": false,
      "key": "US11135F1012",
      "price_usd": 204.81
    },
    {
      "isin": "US5324571083",
      "name": "ELI LILLY & CO",
      "code": "LLY US Equity",
      "ticker": "LLY",
      "weight": 3.3188,
      "shares": 13,
      "amount": 13993997.0,
      "price": null,
      "is_cash": false,
      "key": "US5324571083",
      "price_usd": 776.72
    },
    {
      "isin": "US7710491033",
      "name": "Roblox Coperation",
      "code": "RBLX US Equity",
      "ticker": "RBLX",
      "weight": 3.1265,
      "shares": 136,
      "amount": 13183456.0,
      "price": null,
      "is_cash": false,
      "key": "US7710491033",
      "price_usd": 70.44
    },
    {
      "isin": "US36828A1016",
      "name": "GE Vernova LLC",
      "code": "GEV US Equity",
      "ticker": "GEV",
      "weight": 2.7686,
      "shares": 22,
      "amount": 11674054.0,
      "price": null,
      "is_cash": false,
      "key": "US36828A1016",
      "price_usd": 406.81
    },
    {
      "isin": "US7707001027",
      "name": "Robinhood Markets Inc",
      "code": "HOOD US Equity",
      "ticker": "HOOD",
      "weight": 2.5947,
      "shares": 167,
      "amount": 10941019.0,
      "price": null,
      "is_cash": false,
      "key": "US7707001027",
      "price_usd": 49.99
    },
    {
      "isin": "US01609W1027",
      "name": "ALIBABA GROUP HOLDING-SP ADR",
      "code": "BABA US Equity",
      "ticker": "BABA",
      "weight": 2.5817,
      "shares": 64,
      "amount": 10886104.0,
      "price": null,
      "is_cash": false,
      "key": "US01609W1027",
      "price_usd": 123.23
    },
    {
      "isin": "US0494681010",
      "name": "ATLASSIAN CORP PLC-CLASS A",
      "code": "TEAM US Equity",
      "ticker": "TEAM",
      "weight": 2.3705,
      "shares": 31,
      "amount": 9995369.0,
      "price": null,
      "is_cash": false,
      "key": "US0494681010",
      "price_usd": 205.71
    },
    {
      "isin": "US30303M1027",
      "name": "Meta Platforms Inc-CL A",
      "code": "META US Equity",
      "ticker": "META",
      "weight": 2.2064,
      "shares": 12,
      "amount": 9303746.0,
      "price": null,
      "is_cash": false,
      "key": "US30303M1027",
      "price_usd": 596.81
    },
    {
      "isin": "US18915M1071",
      "name": "Cloudflare Inc",
      "code": "NET US Equity",
      "ticker": "NET",
      "weight": 2.1277,
      "shares": 52,
      "amount": 8971860.0,
      "price": null,
      "is_cash": false,
      "key": "US18915M1071",
      "price_usd": 121.71
    },
    {
      "isin": "US75734B1008",
      "name": "Reddit Inc",
      "code": "RDDT US Equity",
      "ticker": "RDDT",
      "weight": 2.0935,
      "shares": 53,
      "amount": 8827553.0,
      "price": null,
      "is_cash": false,
      "key": "US75734B1008",
      "price_usd": 105.53
    },
    {
      "isin": "US19260Q1076",
      "name": "COINBASE GLOBAL INC -CLASS A",
      "code": "COIN US Equity",
      "ticker": "COIN",
      "weight": 2.0657,
      "shares": 31,
      "amount": 8710087.0,
      "price": null,
      "is_cash": false,
      "key": "US19260Q1076",
      "price_usd": 196.56
    },
    {
      "isin": "US6974351057",
      "name": "PALO ALTO NETWORKS INC",
      "code": "PANW US Equity",
      "ticker": "PANW",
      "weight": 1.9865,
      "shares": 32,
      "amount": 8376487.0,
      "price": null,
      "is_cash": false,
      "key": "US6974351057",
      "price_usd": 188.14
    },
    {
      "isin": "US25809K1051",
      "name": "DOORDASH INC - A",
      "code": "DASH US Equity",
      "ticker": "DASH",
      "weight": 1.9185,
      "shares": 29,
      "amount": 8089620.0,
      "price": null,
      "is_cash": false,
      "key": "US25809K1051",
      "price_usd": 176.99
    },
    {
      "isin": "US98980G1022",
      "name": "ZSCALER INC",
      "code": "ZS US Equity",
      "ticker": "ZS",
      "weight": 1.907,
      "shares": 25,
      "amount": 8041002.0,
      "price": null,
      "is_cash": false,
      "key": "US98980G1022",
      "price_usd": 233.54
    },
    {
      "isin": "US20717M1036",
      "name": "CONFLUENT INC-CLASS A",
      "code": "CFLT US Equity",
      "ticker": "CFLT",
      "weight": 1.7842,
      "shares": 275,
      "amount": 7523115.0,
      "price": null,
      "is_cash": false,
      "key": "US20717M1036"
    },
    {
      "isin": "US88023B1035",
      "name": "Tempus AI Inc",
      "code": "TEM US Equity",
      "ticker": "TEM",
      "weight": 1.5996,
      "shares": 93,
      "amount": 6745094.0,
      "price": null,
      "is_cash": false,
      "key": "US88023B1035",
      "price_usd": 58.76
    },
    {
      "isin": "US26701L1008",
      "name": "Dutch Bros Inc",
      "code": "BROS US Equity",
      "ticker": "BROS",
      "weight": 1.3325,
      "shares": 67,
      "amount": 5618576.0,
      "price": null,
      "is_cash": false,
      "key": "US26701L1008",
      "price_usd": 59.22
    },
    {
      "isin": "US8740541094",
      "name": "TAKE-TWO INTERACTIVE SOFTWRE",
      "code": "TTWO US Equity",
      "ticker": "TTWO",
      "weight": 1.1647,
      "shares": 15,
      "amount": 4910998.0,
      "price": null,
      "is_cash": false,
      "key": "US8740541094",
      "price_usd": 226.34
    },
    {
      "isin": "US19247G1076",
      "name": "COHERENT CORP",
      "code": "COHR US Equity",
      "ticker": "COHR",
      "weight": 1.0226,
      "shares": 44,
      "amount": 4311996.0,
      "price": null,
      "is_cash": false,
      "key": "US19247G1076",
      "price_usd": 69.62
    },
    {
      "isin": "US7731221062",
      "name": "Rocket Lab USA Inc",
      "code": "RKLB US Equity",
      "ticker": "RKLB",
      "weight": 1.0165,
      "shares": 138,
      "amount": 4286343.0,
      "price": null,
      "is_cash": false,
      "key": "US7731221062",
      "price_usd": 22.29
    },
    {
      "isin": "LU1778762911",
      "name": "Spotify Technology SA",
      "code": "SPOT US Equity",
      "ticker": "SPOT",
      "weight": 1.0036,
      "shares": 5,
      "amount": 4231779.0,
      "price": null,
      "is_cash": false,
      "key": "LU1778762911",
      "price_usd": 657.1
    },
    {
      "isin": "US7181721090",
      "name": "PHILIP MORRIS INTERNATIONAL",
      "code": "PM US Equity",
      "ticker": "PM",
      "weight": 0.9816,
      "shares": 17,
      "amount": 4138982.0,
      "price": null,
      "is_cash": false,
      "key": "US7181721090",
      "price_usd": 175.36
    },
    {
      "isin": "US76655K1034",
      "name": "Rigetti Computing Inc",
      "code": "RGTI US Equity",
      "ticker": "RGTI",
      "weight": 0.937,
      "shares": 308,
      "amount": 3951078.0,
      "price": null,
      "is_cash": false,
      "key": "US76655K1034",
      "price_usd": 9.25
    },
    {
      "isin": "US89677Q1076",
      "name": "TRIP.COM GROUP",
      "code": "TCOM US Equity",
      "ticker": "TCOM",
      "weight": 0.8828,
      "shares": 45,
      "amount": 3722557.0,
      "price": null,
      "is_cash": false,
      "key": "US89677Q1076",
      "price_usd": 62.12
    },
    {
      "isin": "US8760301072",
      "name": "TAPESTRY INC",
      "code": "TPR US Equity",
      "ticker": "TPR",
      "weight": 0.8291,
      "shares": 35,
      "amount": 3495813.0,
      "price": null,
      "is_cash": false,
      "key": "US8760301072",
      "price_usd": 74.75
    },
    {
      "isin": "CH1134540470",
      "name": "On Holding AG",
      "code": "ONON US Equity",
      "ticker": "ONON",
      "weight": 0.7276,
      "shares": 46,
      "amount": 3068036.0,
      "price": null,
      "is_cash": false,
      "key": "CH1134540470",
      "price_usd": 48.53
    },
    {
      "isin": "KYG8068L1086",
      "name": "SharkNinja Inc",
      "code": "SN US Equity",
      "ticker": "SN",
      "weight": 0.7105,
      "shares": 27,
      "amount": 2995713.0,
      "price": null,
      "is_cash": false,
      "key": "KYG8068L1086",
      "price_usd": 81.19
    },
    {
      "isin": "US92532F1003",
      "name": "Vertex Pharmaceuticals Inc",
      "code": "VRTX US Equity",
      "ticker": "VRTX",
      "weight": 0.6052,
      "shares": 4,
      "amount": 2551814.0,
      "price": null,
      "is_cash": false,
      "key": "US92532F1003",
      "price_usd": 434.82
    },
    {
      "isin": "CASH00000001",
      "name": "설정현금액",
      "code": "CASH00000001",
      "ticker": "",
      "weight": 0.0,
      "shares": 439903856,
      "amount": 439903856.0,
      "price": null,
      "is_cash": true,
      "key": "CASH00000001"
    },
    {
      "isin": "KRD010010001",
      "name": "원화현금",
      "code": "KRD010010001",
      "ticker": "",
      "weight": 0.0,
      "shares": 18242093,
      "amount": 18242093.0,
      "price": null,
      "is_cash": true,
      "key": "KRD010010001"
    }
  ]
}