{
  "date": "2025-03-06",
  "ticker": "0015B0",
  "fund_id": "2ETFQ1",
  "name": "KoAct 미국나스닥성장기업액티브",
  "count": 31,
  "holdings": [
    {
      "isin": "US02079K3059",
      "name": "ALPHABET INC-CL A",
      "code": "GOOGL US Equity",
      "ticker": "GOOGL",
      "weight": 12.2557,
      "shares": 212,
      "amount": 52626798.0,
      "price": null,
      "is_cash": false,
      "key": "US02079K3059",
      "price_usd": 172.35
    },
    {
      "isin": "US69608A1088",
      "name": "Palantir Technologies Inc -A",
      "code": "PLTR US Equity",
      "ticker": "PLTR",
      "weight": 11.0213,
      "shares": 386,
      "amount": 47326358.0,
      "price": null,
      "is_cash": false,
      "key": "US69608A1088",
      "price_usd": 80.46
    },
    {
      "isin": "US11135F1012",
      "name": "BROADCOM LTD",
      "code": "AVGO US Equity",
      "ticker": "AVGO",
      "weight": 10.0825,
      "shares": 159,
      "amount": 43294937.0,
      "price": null,
      "is_cash": false,
      "key": "US11135F1012",
      "price_usd": 179.45
    },
    {
      "isin": "US3755581036",
      "name": "GILEAD SCIENCES INC",
      "code": "GILD US Equity",
      "ticker": "GILD",
      "weight": 4.5705,
      "shares": 118,
      "amount": 19626185.0,
      "price": null,
      "is_cash": false,
      "key": "US3755581036",
      "price_usd": 116.04
    },
    {
      "isin": "US67066G1040",
      "name": "NVIDIA Corp",
      "code": "NVDA US Equity",
      "ticker": "NVDA",
      "weight": 4.2915,
      "shares": 109,
      "amount": 18427915.0,
      "price": null,
      "is_cash": false,
      "key": "US67066G1040",
      "price_usd": 110.57
    },
    {
      "isin": "US92532F1003",
      "name": "Vertex Pharmaceuticals Inc",
      "code": "VRTX US Equity",
      "ticker": "VRTX",
      "weight": 4.1618,
      "shares": 25,
      "amount": 17871120.0,
      "price": null,
      "is_cash": false,
      "key": "US92532F1003",
      "price_usd": 485.72
    },
    {
      "isin": "US8760301072",
      "name": "TAPESTRY INC",
      "code": "TPR US Equity",
      "ticker": "TPR",
      "weight": 3.7163,
      "shares": 135,
      "amount": 15957974.0,
      "price": null,
      "is_cash": false,
      "key": "US8760301072",
      "price_usd": 77.72
    },
    {
      "isin": "US1101221083",
      "name": "BRISTOL-MYERS SQUIBB CO",
      "code": "BMY US Equity",
      "ticker": "BMY",
      "weight": 3.4475,
      "shares": 171,
      "amount": 14803771.0,
      "price": null,
      "is_cash": false,
      "key": "US1101221083",
      "price_usd": 60.18
    },
    {
      "isin": "US61174X1090",
      "name": "MONSTER BEVERAGE CORP",
      "code": "MNST US Equity",
      "ticker": "MNST",
      "weight": 2.9261,
      "shares": 158,
      "amount": 12564750.0,
      "price": null,
      "is_cash": false,
      "key": "US61174X1090",
      "price_usd": 55.69
    },
    {
      "isin": "US01609W1027",
      "name": "ALIBABA GROUP HOLDING-SP ADR",
      "code": "BABA US Equity",
      "ticker": "BABA",
      "weight": 2.9196,
      "shares": 66,
      "amount": 12536979.0,
      "price": null,
      "is_cash": false,
      "key": "US01609W1027",
      "price_usd": 139.95
    },
    {
      "isin": "US49271V1008",
      "name": "KEURIG DR PEPPER",
      "code": "KDP US Equity",
      "ticker": "KDP",
      "weight": 2.8588,
      "shares": 251,
      "amount": 12275956.0,
      "price": null,
      "is_cash": false,
      "key": "US49271V1008",
      "price_usd": 33.53
    },
    {
      "isin": "US64110L1061",
      "name": "NETFLIX",
      "code": "NFLX US Equity",
      "ticker": "NFLX",
      "weight": 2.8002,
      "shares": 8,
      "amount": 12024249.0,
      "price": null,
      "is_cash": false,
      "key": "US64110L1061",
      "price_usd": 90.64
    },
    {
      "isin": "CA82509L1076",
      "name": "Shopify Inc",
      "code": "SHOP US Equity",
      "ticker": "SHOP",
      "weight": 2.4586,
      "shares": 71,
      "amount": 10557394.0,
      "price": null,
      "is_cash": false,
      "key": "CA82509L1076",
      "price_usd": 102.49
    },
    {
      "isin": "LU1778762911",
      "name": "Spotify Technology SA",
      "code": "SPOT US Equity",
      "ticker": "SPOT",
      "weight": 2.4495,
      "shares": 12,
      "amount": 10518439.0,
      "price": null,
      "is_cash": false,
      "key": "LU1778762911",
      "price_usd": 543.41
    },
    {
      "isin": "US26701L1008",
      "name": "Dutch Bros Inc",
      "code": "BROS US Equity",
      "ticker": "BROS",
      "weight": 2.4253,
      "shares": 99,
      "amount": 10414251.0,
      "price": null,
      "is_cash": false,
      "key": "US26701L1008",
      "price_usd": 64.78
    },
    {
      "isin": "US04351P1012",
      "name": "Ascendis Pharma A/S",
      "code": "ASND US Equity",
      "ticker": "ASND",
      "weight": 2.4193,
      "shares": 47,
      "amount": 10388564.0,
      "price": null,
      "is_cash": false,
      "key": "US04351P1012",
      "price_usd": 151.51
    },
    {
      "isin": "US46120E6023",
      "name": "Intuitive Surgical Inc",
      "code": "ISRG US Equity",
      "ticker": "ISRG",
      "weight": 2.1697,
      "shares": 11,
      "amount": 9316626.0,
      "price": null,
      "is_cash": false,
      "key": "US46120E6023",
      "price_usd": 538.57
    },
    {
      "isin": "US04016X1019",
      "name": "Argenx SE",
      "code": "ARGX US Equity",
      "ticker": "ARGX",
      "weight": 2.1233,
      "shares": 10,
      "amount": 9117405.0,
      "price": null,
      "is_cash": false,
      "key": "US04016X1019",
      "price_usd": 613.18
    },
    {
      "isin": "US0255371017",
      "name": "AMERICAN ELECTRIC POWER",
      "code": "AEP US Equity",
      "ticker": "AEP",
      "weight": 2.1142,
      "shares": 59,
      "amount": 9078675.0,
      "price": null,
      "is_cash": false,
      "key": "US0255371017",
      "price_usd": 102.59
    },
    {
      "isin": "US30303M1027",
      "name": "Meta Platforms Inc-CL A",
      "code": "META US Equity",
      "ticker": "META",
      "weight": 2.0551,
      "shares": 9,
      "amount": 8824742.0,
      "price": null,
      "is_cash": false,
      "key": "US30303M1027",
      "price_usd": 627.93
    },
    {
      "isin": "US9311421039",
      "name": "WAL-MART STORES INC",
      "code": "WMT US Equity",
      "ticker": "WMT",
      "weight": 1.9475,
      "shares": 61,
      "amount": 8362624.0,
      "price": null,
      "is_cash": false,
      "key": "US9311421039",
      "price_usd": 94.64
    },
    {
      "isin": "US6974351057",
      "name": "PALO ALTO NETWORKS INC",
      "code": "PANW US Equity",
      "ticker": "PANW",
      "weight": 1.9429,
      "shares": 31,
      "amount": 8343101.0,
      "price": null,
      "is_cash": false,
      "key": "US6974351057",
      "price_usd": 179.33
    },
    {
      "isin": "US58733R1023",
      "name": "MERCADOLIBRE",
      "code": "MELI US Equity",
      "ticker": "MELI",
      "weight": 1.8141,
      "shares": 3,
      "amount": 7789810.0,
      "price": null,
      "is_cash": false,
      "key": "US58733R1023",
      "price_usd": 2045.25
    },
    {
      "isin": "US20717M1036",
      "name": "CONFLUENT INC-CLASS A",
      "code": "CFLT US Equity",
      "ticker": "CFLT",
      "weight": 1.7213,
      "shares": 170,
      "amount": 7391225.0,
      "price": null,
      "is_cash": false,
      "key": "US20717M1036"
    },
    {
      "isin": "US0378331005",
      "name": "APPLE Inc",
      "code": "AAPL US Equity",
      "ticker": "AAPL",
      "weight": 1.5368,
      "shares": 19,
      "amount": 6598970.0,
      "price": null,
      "is_cash": false,
      "key": "US0378331005",
      "price_usd": 235.33
    },
    {
      "isin": "US36828A1016",
      "name": "GE Vernova LLC",
      "code": "GEV US Equity",
      "ticker": "GEV",
      "weight": 1.5292,
      "shares": 14,
      "amount": 6566295.0,
      "price": null,
      "is_cash": false,
      "key": "US36828A1016",
      "price_usd": 293.21
    },
    {
      "isin": "US88160R1014",
      "name": "TESLA MOTORS",
      "code": "TSLA US Equity",
      "ticker": "TSLA",
      "weight": 1.4375,
      "shares": 16,
      "amount": 6172642.0,
      "price": null,
      "is_cash": false,
      "key": "US88160R1014",
      "price_usd": 263.45
    },
    {
      "isin": "US8740541094",
      "name": "TAKE-TWO INTERACTIVE SOFTWRE",
      "code": "TTWO US Equity",
      "ticker": "TTWO",
      "weight": 1.4036,
      "shares": 20,
      "amount": 6027285.0,
      "price": null,
      "is_cash": false,
      "key": "US8740541094",
      "price_usd": 207.87
    },
    {
      "isin": "US4581401001",
      "name": "INTEL Corp",
      "code": "INTC US Equity",
      "ticker": "INTC",
      "weight": 1.2366,
      "shares": 171,
      "amount": 5309840.0,
      "price": null,
      "is_cash": false,
      "key": "US4581401001",
      "price_usd": 20.75
    },
    {
      "isin": "US0231351067",
      "name": "Amazon.com Inc",
      "code": "AMZN US Equity",
      "ticker": "AMZN",
      "weight": 1.1956,
      "shares": 17,
      "amount": 5134117.0,
      "price": null,
      "is_cash": false,
      "key": "US0231351067",
      "price_usd": 200.7
    },
    {
      "isin": "US92333F1012",
      "name": "Venture Global Inc",
      "code": "VG US Equity",
      "ticker": "VG",
      "weight": 0.9682,
      "shares": 208,
      "amount": 4157308.0,
      "price": null,
      "is_cash": false,
      "key": "US92333F1012",
      "price_usd": 9.1
    },
    {
      "isin": "CASH00000001",
      "name": "설정현금액",
      "code": "CASH00000001",
      "ticker": "",
      "weight": 0.0,
      "shares": 452008022,
      "amount": 452008022.0,
      "price": null,
      "is_cash": true,
      "key": "CASH00000001"
    },
    {
      "isin": "KRD010010001",
      "name": "원화현금",
      "code": "KRD010010001",
      "ticker": "",
      "weight": 0.0,
      "shares": 22601717,
      "amount": 22601717.0,
      "price": null,
      "is_cash": true,
      "key": "KRD010010001"
    }
  ]
}