{
  "date": "2025-03-17",
  "ticker": "0015B0",
  "fund_id": "2ETFQ1",
  "name": "KoAct 미국나스닥성장기업액티브",
  "count": 35,
  "holdings": [
    {
      "isin": "US02079K3059",
      "name": "ALPHABET INC-CL A",
      "code": "GOOGL US Equity",
      "ticker": "GOOGL",
      "weight": 10.7059,
      "shares": 194,
      "amount": 45878346.0,
      "price": null,
      "is_cash": false,
      "key": "US02079K3059",
      "price_usd": 164.29
    },
    {
      "isin": "US69608A1088",
      "name": "Palantir Technologies Inc -A",
      "code": "PLTR US Equity",
      "ticker": "PLTR",
      "weight": 10.5895,
      "shares": 392,
      "amount": 45379240.0,
      "price": null,
      "is_cash": false,
      "key": "US69608A1088",
      "price_usd": 87.35
    },
    {
      "isin": "US11135F1012",
      "name": "BROADCOM LTD",
      "code": "AVGO US Equity",
      "ticker": "AVGO",
      "weight": 10.2988,
      "shares": 159,
      "amount": 44133516.0,
      "price": null,
      "is_cash": false,
      "key": "US11135F1012",
      "price_usd": 194.5
    },
    {
      "isin": "US67066G1040",
      "name": "NVIDIA Corp",
      "code": "NVDA US Equity",
      "ticker": "NVDA",
      "weight": 7.9257,
      "shares": 202,
      "amount": 33963945.0,
      "price": null,
      "is_cash": false,
      "key": "US67066G1040",
      "price_usd": 119.53
    },
    {
      "isin": "US01609W1027",
      "name": "ALIBABA GROUP HOLDING-SP ADR",
      "code": "BABA US Equity",
      "ticker": "BABA",
      "weight": 4.8428,
      "shares": 103,
      "amount": 20752926.0,
      "price": null,
      "is_cash": false,
      "key": "US01609W1027",
      "price_usd": 147.57
    },
    {
      "isin": "US92532F1003",
      "name": "Vertex Pharmaceuticals Inc",
      "code": "VRTX US Equity",
      "ticker": "VRTX",
      "weight": 3.9242,
      "shares": 23,
      "amount": 16816337.0,
      "price": null,
      "is_cash": false,
      "key": "US92532F1003",
      "price_usd": 513.76
    },
    {
      "isin": "US1101221083",
      "name": "BRISTOL-MYERS SQUIBB CO",
      "code": "BMY US Equity",
      "ticker": "BMY",
      "weight": 3.2538,
      "shares": 159,
      "amount": 13943615.0,
      "price": null,
      "is_cash": false,
      "key": "US1101221083",
      "price_usd": 59.99
    },
    {
      "isin": "US61174X1090",
      "name": "MONSTER BEVERAGE CORP",
      "code": "MNST US Equity",
      "ticker": "MNST",
      "weight": 3.2101,
      "shares": 174,
      "amount": 13756181.0,
      "price": null,
      "is_cash": false,
      "key": "US61174X1090",
      "price_usd": 56.21
    },
    {
      "isin": "US3755581036",
      "name": "GILEAD SCIENCES INC",
      "code": "GILD US Equity",
      "ticker": "GILD",
      "weight": 3.1644,
      "shares": 82,
      "amount": 13560423.0,
      "price": null,
      "is_cash": false,
      "key": "US3755581036",
      "price_usd": 112.26
    },
    {
      "isin": "US49271V1008",
      "name": "KEURIG DR PEPPER",
      "code": "KDP US Equity",
      "ticker": "KDP",
      "weight": 3.1386,
      "shares": 279,
      "amount": 13449970.0,
      "price": null,
      "is_cash": false,
      "key": "US49271V1008",
      "price_usd": 33.84
    },
    {
      "isin": "US36828A1016",
      "name": "GE Vernova LLC",
      "code": "GEV US Equity",
      "ticker": "GEV",
      "weight": 2.7501,
      "shares": 27,
      "amount": 11785200.0,
      "price": null,
      "is_cash": false,
      "key": "US36828A1016",
      "price_usd": 331.96
    },
    {
      "isin": "US88160R1014",
      "name": "TESLA MOTORS",
      "code": "TSLA US Equity",
      "ticker": "TSLA",
      "weight": 2.5296,
      "shares": 31,
      "amount": 10839920.0,
      "price": null,
      "is_cash": false,
      "key": "US88160R1014",
      "price_usd": 238.01
    },
    {
      "isin": "US64110L1061",
      "name": "NETFLIX",
      "code": "NFLX US Equity",
      "ticker": "NFLX",
      "weight": 2.1472,
      "shares": 7,
      "amount": 9201258.0,
      "price": null,
      "is_cash": false,
      "key": "US64110L1061",
      "price_usd": 95.0
    },
    {
      "isin": "CA82509L1076",
      "name": "Shopify Inc",
      "code": "SHOP US Equity",
      "ticker": "SHOP",
      "weight": 2.064,
      "shares": 67,
      "amount": 8844954.0,
      "price": null,
      "is_cash": false,
      "key": "CA82509L1076",
      "price_usd": 96.59
    },
    {
      "isin": "LU1778762911",
      "name": "Spotify Technology SA",
      "code": "SPOT US Equity",
      "ticker": "SPOT",
      "weight": 2.0603,
      "shares": 11,
      "amount": 8828933.0,
      "price": null,
      "is_cash": false,
      "key": "LU1778762911",
      "price_usd": 597.46
    },
    {
      "isin": "US0255371017",
      "name": "AMERICAN ELECTRIC POWER",
      "code": "AEP US Equity",
      "ticker": "AEP",
      "weight": 1.9528,
      "shares": 55,
      "amount": 8368265.0,
      "price": null,
      "is_cash": false,
      "key": "US0255371017",
      "price_usd": 105.86
    },
    {
      "isin": "US81141R1005",
      "name": "SEA LIMITED ADS EACH REP ONE CLASS",
      "code": "SE US Equity",
      "ticker": "SE",
      "weight": 1.8575,
      "shares": 44,
      "amount": 7960157.0,
      "price": null,
      "is_cash": false,
      "key": "US81141R1005",
      "price_usd": 132.64
    },
    {
      "isin": "US09062X1037",
      "name": "BIOGEN",
      "code": "BIIB US Equity",
      "ticker": "BIIB",
      "weight": 1.8573,
      "shares": 39,
      "amount": 7958999.0,
      "price": null,
      "is_cash": false,
      "key": "US09062X1037",
      "price_usd": 143.54
    },
    {
      "isin": "US26701L1008",
      "name": "Dutch Bros Inc",
      "code": "BROS US Equity",
      "ticker": "BROS",
      "weight": 1.8249,
      "shares": 90,
      "amount": 7820290.0,
      "price": null,
      "is_cash": false,
      "key": "US26701L1008",
      "price_usd": 61.94
    },
    {
      "isin": "US30303M1027",
      "name": "Meta Platforms Inc-CL A",
      "code": "META US Equity",
      "ticker": "META",
      "weight": 1.7773,
      "shares": 9,
      "amount": 7616424.0,
      "price": null,
      "is_cash": false,
      "key": "US30303M1027",
      "price_usd": 604.9
    },
    {
      "isin": "KYG254571055",
      "name": "Credo Technology Group Holding Ltd",
      "code": "CRDO US Equity",
      "ticker": "CRDO",
      "weight": 1.7567,
      "shares": 115,
      "amount": 7528125.0,
      "price": null,
      "is_cash": false,
      "key": "KYG254571055",
      "price_usd": 47.02
    },
    {
      "isin": "US4581401001",
      "name": "INTEL Corp",
      "code": "INTC US Equity",
      "ticker": "INTC",
      "weight": 1.7221,
      "shares": 214,
      "amount": 7379584.0,
      "price": null,
      "is_cash": false,
      "key": "US4581401001",
      "price_usd": 25.69
    },
    {
      "isin": "US46120E6023",
      "name": "Intuitive Surgical Inc",
      "code": "ISRG US Equity",
      "ticker": "ISRG",
      "weight": 1.5528,
      "shares": 10,
      "amount": 6654170.0,
      "price": null,
      "is_cash": false,
      "key": "US46120E6023",
      "price_usd": 488.8
    },
    {
      "isin": "KYG0567U1278",
      "name": "Arqit Quantum Inc",
      "code": "ARQQ US Equity",
      "ticker": "ARQQ",
      "weight": 1.452,
      "shares": 330,
      "amount": 6222409.0,
      "price": null,
      "is_cash": false,
      "key": "KYG0567U1278",
      "price_usd": 23.54
    },
    {
      "isin": "US20717M1036",
      "name": "CONFLUENT INC-CLASS A",
      "code": "CFLT US Equity",
      "ticker": "CFLT",
      "weight": 1.403,
      "shares": 160,
      "amount": 6012163.0,
      "price": null,
      "is_cash": false,
      "key": "US20717M1036"
    },
    {
      "isin": "US19260Q1076",
      "name": "COINBASE GLOBAL INC -CLASS A",
      "code": "COIN US Equity",
      "ticker": "COIN",
      "weight": 1.2952,
      "shares": 22,
      "amount": 5550332.0,
      "price": null,
      "is_cash": false,
      "key": "US19260Q1076",
      "price_usd": 188.96
    },
    {
      "isin": "US8740541094",
      "name": "TAKE-TWO INTERACTIVE SOFTWRE",
      "code": "TTWO US Equity",
      "ticker": "TTWO",
      "weight": 1.2773,
      "shares": 18,
      "amount": 5473729.0,
      "price": null,
      "is_cash": false,
      "key": "US8740541094",
      "price_usd": 206.5
    },
    {
      "isin": "US26740W1099",
      "name": "D-Wave Quantum Inc",
      "code": "QBTS US Equity",
      "ticker": "QBTS",
      "weight": 1.1909,
      "shares": 508,
      "amount": 5103245.0,
      "price": null,
      "is_cash": false,
      "key": "US26740W1099",
      "price_usd": 11.18
    },
    {
      "isin": "US8760301072",
      "name": "TAPESTRY INC",
      "code": "TPR US Equity",
      "ticker": "TPR",
      "weight": 1.0384,
      "shares": 44,
      "amount": 4450032.0,
      "price": null,
      "is_cash": false,
      "key": "US8760301072",
      "price_usd": 71.22
    },
    {
      "isin": "KYG8068L1086",
      "name": "SharkNinja Inc",
      "code": "SN US Equity",
      "ticker": "SN",
      "weight": 0.9806,
      "shares": 33,
      "amount": 4202282.0,
      "price": null,
      "is_cash": false,
      "key": "KYG8068L1086",
      "price_usd": 90.02
    },
    {
      "isin": "US04351P1012",
      "name": "Ascendis Pharma A/S",
      "code": "ASND US Equity",
      "ticker": "ASND",
      "weight": 0.975,
      "shares": 19,
      "amount": 4178351.0,
      "price": null,
      "is_cash": false,
      "key": "US04351P1012",
      "price_usd": 168.84
    },
    {
      "isin": "US98980G1022",
      "name": "ZSCALER INC",
      "code": "ZS US Equity",
      "ticker": "ZS",
      "weight": 0.8959,
      "shares": 14,
      "amount": 3839266.0,
      "price": null,
      "is_cash": false,
      "key": "US98980G1022",
      "price_usd": 202.65
    },
    {
      "isin": "CH1134540470",
      "name": "On Holding AG",
      "code": "ONON US Equity",
      "ticker": "ONON",
      "weight": 0.8956,
      "shares": 57,
      "amount": 3837805.0,
      "price": null,
      "is_cash": false,
      "key": "CH1134540470",
      "price_usd": 48.06
    },
    {
      "isin": "US04016X1019",
      "name": "Argenx SE",
      "code": "ARGX US Equity",
      "ticker": "ARGX",
      "weight": 0.8932,
      "shares": 5,
      "amount": 3827682.0,
      "price": null,
      "is_cash": false,
      "key": "US04016X1019",
      "price_usd": 614.19
    },
    {
      "isin": "US58733R1023",
      "name": "MERCADOLIBRE",
      "code": "MELI US Equity",
      "ticker": "MELI",
      "weight": 0.7965,
      "shares": 1,
      "amount": 3413298.0,
      "price": null,
      "is_cash": false,
      "key": "US58733R1023",
      "price_usd": 2106.46
    },
    {
      "isin": "CASH00000001",
      "name": "설정현금액",
      "code": "CASH00000001",
      "ticker": "",
      "weight": 0.0,
      "shares": 430997314,
      "amount": 430997314.0,
      "price": null,
      "is_cash": true,
      "key": "CASH00000001"
    },
    {
      "isin": "KRD010010001",
      "name": "원화현금",
      "code": "KRD010010001",
      "ticker": "",
      "weight": 0.0,
      "shares": 2465942,
      "amount": 2465942.0,
      "price": null,
      "is_cash": true,
      "key": "KRD010010001"
    }
  ]
}